README.md
setup.cfg
setup.py
Othello_Python/__init__.py
Othello_Python/othello_execution.py
Othello_Python.egg-info/PKG-INFO
Othello_Python.egg-info/SOURCES.txt
Othello_Python.egg-info/dependency_links.txt
Othello_Python.egg-info/entry_points.txt
Othello_Python.egg-info/not-zip-safe
Othello_Python.egg-info/top_level.txt