Metadata-Version: 1.1
Name: Othello-Python
Version: 0.1
Summary: A Python implementation of Othello
Home-page: UNKNOWN
Author: Daniel Burns
Author-email: danieljburns143@gmail.com
License: MIT
Download-URL: https://github.com/danieljburns143/Othello_Python/archive/0.1.tar.gz
Platform: UNKNOWN
